custom_json_diff/__init__.py
custom_json_diff/cli.py
custom_json_diff/lib/__init__.py
custom_json_diff/lib/bom_diff_template.j2
custom_json_diff/lib/bom_diff_template_minimal.j2
custom_json_diff/lib/csaf_diff_template.j2
custom_json_diff/lib/custom_diff.py
custom_json_diff/lib/custom_diff_classes.py
custom_json_diff/lib/utils.py
custom_json_diff-2.1.6.dist-info/LICENSE
custom_json_diff-2.1.6.dist-info/METADATA
custom_json_diff-2.1.6.dist-info/WHEEL
custom_json_diff-2.1.6.dist-info/entry_points.txt
custom_json_diff-2.1.6.dist-info/top_level.txt
custom_json_diff-2.1.6.dist-info/RECORD
