Metadata-Version: 2.2
Name: custom-json-diff
Version: 2.1.6
Summary: CycloneDx BOM and Oasis CSAF diffing and comparison tool.
Author-email: Caroline Russell <caroline@appthreat.dev>
License: Apache-2.0
Project-URL: Homepage, https://github.com/appthreat/custom-json-diff
Project-URL: Bug Tracker, https://github.com/appthreat/custom-json-diff/issues
Project-URL: Funding, https://github.com/sponsors/cerrussell
Classifier: Programming Language :: Python :: 3.10
Classifier: Programming Language :: Python :: 3.11
Classifier: Programming Language :: Python :: 3.12
Classifier: License :: OSI Approved :: Apache Software License
Classifier: Development Status :: 5 - Production/Stable
Classifier: Intended Audience :: Developers
Classifier: Operating System :: OS Independent
Classifier: Environment :: Console
Classifier: Topic :: Utilities
Classifier: Topic :: File Formats :: JSON
Requires-Python: >=3.10
License-File: LICENSE
Requires-Dist: jinja2>=3.1.4
Requires-Dist: json-flatten>=0.3
Requires-Dist: packageurl-python>=0.15.6
Requires-Dist: semver>=3.0.0
Requires-Dist: toml>=0.10
Provides-Extra: dev
Requires-Dist: mypy; extra == "dev"
Requires-Dist: pytest; extra == "dev"
